twiggy_goodies/__init__.py
twiggy_goodies/django.py
twiggy_goodies/django_rq.py
twiggy_goodies/json.py
twiggy_goodies/logstash.py
twiggy_goodies/setup.py
twiggy_goodies/std_logging.py
twiggy_goodies/syslog.py
twiggy_goodies/threading.py
twiggy_goodies-0.6.0.dist-info/DESCRIPTION.rst
twiggy_goodies-0.6.0.dist-info/METADATA
twiggy_goodies-0.6.0.dist-info/metadata.json
twiggy_goodies-0.6.0.dist-info/RECORD
twiggy_goodies-0.6.0.dist-info/top_level.txt
twiggy_goodies-0.6.0.dist-info/WHEEL
twiggy_goodies-0.6.0.dist-info/zip-safe
