Metadata-Version: 2.0
Name: twiggy-goodies
Version: 0.6.0
Summary: Handlers and helpers for Twiggy logging library.
Home-page: https://github.com/svetlyak40wt/twiggy-goodies
Author: Alexander Artemenko
Author-email: svetlyak.40wt@gmail.com
License: BSD
Keywords: logging
Platform: UNKNOWN
Classifier: Development Status :: 3 - Alpha
Classifier: Intended Audience :: Developers
Classifier: Topic :: System :: Logging
Classifier: License :: OSI Approved :: BSD License
Classifier: Programming Language :: Python
Classifier: Programming Language :: Python :: 2
Classifier: Programming Language :: Python :: 2.7
Requires-Dist: twiggy (<0.5.0)
Requires-Dist: pytz
Requires-Dist: anyjson
Requires-Dist: six
